depict_control/__init__.py
depict_control/frame.py
depict_control-1.0.dist-info/LICENSE
depict_control-1.0.dist-info/METADATA
depict_control-1.0.dist-info/WHEEL
depict_control-1.0.dist-info/top_level.txt
depict_control-1.0.dist-info/RECORD
