Metadata-Version: 2.1
Name: depict-control
Version: 1.0
Summary: Control your Depict digital art frames (depict.com)
Home-page: https://github.com/jkeljo/depict-control
Author: Jonathan Keljo
License: UNKNOWN
Keywords: depict
Platform: UNKNOWN
Classifier: Development Status :: 4 - Beta
Classifier: Intended Audience :: Developers
Classifier: Topic :: Home Automation
Classifier: License :: OSI Approved :: MIT License
Classifier: Programming Language :: Python :: 3.5
Requires-Python: >=3.5.1
Requires-Dist: aiohttp
Requires-Dist: netifaces
